MANIFEST.in
README.rst
requirements.txt
setup.py
vanilla/__init__.py
vanilla/consul.py
vanilla.consul.egg-info/PKG-INFO
vanilla.consul.egg-info/SOURCES.txt
vanilla.consul.egg-info/dependency_links.txt
vanilla.consul.egg-info/namespace_packages.txt
vanilla.consul.egg-info/requires.txt
vanilla.consul.egg-info/top_level.txt