Metadata-Version: 1.0
Name: vanilla.consul
Version: 0.4.2
Summary: Vanilla Python client for Consul.io
Home-page: https://github.com/cablehead/vanilla.consul
Author: Andy Gayton
Author-email: andy@thecablelounge.com
License: MIT
Platform: UNKNOWN
